geek_web_man.py
geek_web_man-0.0.1.0.dist-info/LICENSE
geek_web_man-0.0.1.0.dist-info/METADATA
geek_web_man-0.0.1.0.dist-info/WHEEL
geek_web_man-0.0.1.0.dist-info/entry_points.txt
geek_web_man-0.0.1.0.dist-info/RECORD
