Metadata-Version: 2.1
Name: geek-web-man
Version: 0.0.1.0
Summary: 极客营Web助手，执行网站性能测试、批量请求URL等任务并生成运行报告
Home-page: https://github.com/geekcampchina/geek-web-man
License: MIT
Author: FifiLyu
Author-email: fifilyu@gmail.com
Requires-Python: >=3.8.5,<4.0.0
Classifier: Intended Audience :: Developers
Classifier: License :: OSI Approved :: MIT License
Classifier: Operating System :: OS Independent
Classifier: Programming Language :: Python
Classifier: Programming Language :: Python :: 3
Classifier: Programming Language :: Python :: 3.9
Classifier: Programming Language :: Python :: 3.10
Classifier: Programming Language :: Python :: 3.11
Classifier: Topic :: System :: System Shells
Requires-Dist: beautifulsoup4 (>=4.12.2)
Requires-Dist: happy-python (>=0.4.7)
Requires-Dist: lxml (>=4.9.3)
Requires-Dist: pytest (>=7.4.1)
Requires-Dist: requests (>=2.31.0)
Requires-Dist: validators (>=0.22.0)
Project-URL: Documentation, https://github.com/geekcampchina/geek-web-man
Project-URL: Repository, https://github.com/geekcampchina/geek-web-man
